MouseTracks_Generate/__init__.py
MouseTracks_Generate/generate.py
MouseTracks_Generate/length_analysis.csv
MouseTracks_Generate/model2.h5
MouseTracks_Generate-1.6.dist-info/LICENCE
MouseTracks_Generate-1.6.dist-info/METADATA
MouseTracks_Generate-1.6.dist-info/WHEEL
MouseTracks_Generate-1.6.dist-info/top_level.txt
MouseTracks_Generate-1.6.dist-info/RECORD
