Metadata-Version: 2.1
Name: MouseTracks-Generate
Version: 1.6
Author: momo
Classifier: Programming Language :: Python :: 3
Classifier: License :: OSI Approved :: MIT License
Classifier: Operating System :: OS Independent
License-File: LICENCE
Requires-Dist: pandas
Requires-Dist: numpy
Requires-Dist: keras
Requires-Dist: tensorflow
Requires-Dist: pyautogui
